CHANGES.md
LICENSE
MANIFEST.in
README.rst
requirements.txt
setup.cfg
setup.py
versioneer.py
photon_pump.egg-info/PKG-INFO
photon_pump.egg-info/SOURCES.txt
photon_pump.egg-info/dependency_links.txt
photon_pump.egg-info/requires.txt
photon_pump.egg-info/top_level.txt
photonpump/__init__.py
photonpump/_version.py
photonpump/compat.py
photonpump/connection.py
photonpump/conversations.py
photonpump/discovery.py
photonpump/exceptions.py
photonpump/messages.py
photonpump/messages_pb2.py