Metadata-Version: 2.1
Name: photon-pump
Version: 0.9.5
Summary: Fast, easy to use client for EventStore
Home-page: http://github.com/madedotcom/photon-pump/
Author: Bob Gregory
Author-email: bob@made.com
License: MIT
Platform: any
Classifier: Programming Language :: Python
Classifier: Development Status :: 3 - Alpha
Classifier: Natural Language :: English
Classifier: Environment :: Web Environment
Classifier: Intended Audience :: Developers
Classifier: License :: OSI Approved :: MIT License
Classifier: Operating System :: OS Independent
Classifier: Topic :: Software Development :: Libraries :: Python Modules
Classifier: Topic :: Software Development :: Libraries :: Application Frameworks
Provides-Extra: testing
License-File: LICENSE
